mixit/__init__.py
mixit/base.py
mixit/core.py
mixit/decorators.py
mixit/exceptions.py
mixit-0.6.0.dist-info/licenses/LICENSE
mixit-0.6.0.dist-info/METADATA
mixit-0.6.0.dist-info/WHEEL
mixit-0.6.0.dist-info/top_level.txt
mixit-0.6.0.dist-info/RECORD
