Metadata-Version: 2.4
Name: mixit
Version: 0.6.0
Summary: A simple mixin system with method exports
Home-page: https://github.com/joshms123/mixit
Author: joshms123
Author-email: dev@joshms.net
License: MIT
Project-URL: Bug Tracker, https://github.com/joshms123/mixit/issues
Project-URL: Source Code, https://github.com/joshms123/mixit
Keywords: mixin,composition,python
Classifier: Development Status :: 4 - Beta
Classifier: Intended Audience :: Developers
Classifier: License :: OSI Approved :: MIT License
Classifier: Programming Language :: Python :: 3
Classifier: Programming Language :: Python :: 3.7
Classifier: Programming Language :: Python :: 3.8
Classifier: Programming Language :: Python :: 3.9
Classifier: Programming Language :: Python :: 3.10
Classifier: Programming Language :: Python :: 3.11
Classifier: Topic :: Software Development :: Libraries :: Python Modules
Requires-Python: >=3.7
License-File: LICENSE
Provides-Extra: dev
Requires-Dist: pytest>=6.0; extra == "dev"
Dynamic: author
Dynamic: author-email
Dynamic: classifier
Dynamic: home-page
Dynamic: keywords
Dynamic: license-file
Dynamic: provides-extra
Dynamic: requires-python
Dynamic: summary
